datafed_torchflow/JSON.py
datafed_torchflow/__init__.py
datafed_torchflow/computer.py
datafed_torchflow/datafed.py
datafed_torchflow/pytorch.py
datafed_torchflow/utils.py
DataFed_TorchFlow-0.2.5.dist-info/METADATA
DataFed_TorchFlow-0.2.5.dist-info/WHEEL
DataFed_TorchFlow-0.2.5.dist-info/top_level.txt
DataFed_TorchFlow-0.2.5.dist-info/RECORD
