Metadata-Version: 2.1
Name: DataFed_TorchFlow
Version: 0.2.5
Summary: Add a short description here!
Home-page: https://github.com/pyscaffold/pyscaffold/
Author: jagar2
Author-email: jca92@drexel.edu
License: MIT
Project-URL: Documentation, https://pyscaffold.org/
Platform: any
Classifier: Development Status :: 4 - Beta
Classifier: Programming Language :: Python
Requires-Dist: GPutil
Requires-Dist: psutil
Requires-Dist: datafed
Requires-Dist: torch
Requires-Dist: torchvision
Requires-Dist: m3learning-util
Requires-Dist: importlib-metadata ; python_version < "3.8"
Provides-Extra: testing
Requires-Dist: setuptools ; extra == 'testing'
Requires-Dist: pytest ; extra == 'testing'
Requires-Dist: pytest-cov ; extra == 'testing'
